<?xml version="1.0" encoding="EUC-KR"?>
<root>
	<Date>2019-04-20</Date>
	<RoundCount>6</RoundCount>
	<Account>
		<UID>23</UID>
		<Time>14:22:54</Time>
		<Name>쟈니</Name>
		<Amount>1</Amount>
		<Bill>0</Bill>
		<Tags>콕 판매(카뱅)</Tags>
	</Account>
	<Account>
		<UID>22</UID>
		<Time>14:22:32</Time>
		<Name>지성</Name>
		<Amount>1</Amount>
		<Bill>15000</Bill>
		<Tags>콕 판매</Tags>
	</Account>
	<Account>
		<UID>21</UID>
		<Time>14:16:33</Time>
		<Name>지성</Name>
		<Amount>0</Amount>
		<Bill>5000</Bill>
		<Tags>일일 입장료</Tags>
	</Account>
	<Account>
		<UID>20</UID>
		<Time>14:04:01</Time>
		<Name>트윈스</Name>
		<Amount>0</Amount>
		<Bill>5000</Bill>
		<Tags>일일 입장료</Tags>
	</Account>
	<Account>
		<UID>19</UID>
		<Time>13:56:51</Time>
		<Name>산타</Name>
		<Amount>0</Amount>
		<Bill>0</Bill>
		<Tags>일일 입장료 (카뱅)</Tags>
	</Account>
	<Account>
		<UID>18</UID>
		<Time>13:56:33</Time>
		<Name>우솔</Name>
		<Amount>0</Amount>
		<Bill>5000</Bill>
		<Tags>일일 입장료</Tags>
	</Account>
	<Account>
		<UID>17</UID>
		<Time>13:41:48</Time>
		<Name>사오</Name>
		<Amount>1</Amount>
		<Bill>16000</Bill>
		<Tags>콕 판매</Tags>
	</Account>
	<Account>
		<UID>16</UID>
		<Time>13:40:15</Time>
		<Name>제로</Name>
		<Amount>1</Amount>
		<Bill>15000</Bill>
		<Tags>콕 판매</Tags>
	</Account>
	<Account>
		<UID>15</UID>
		<Time>13:40:06</Time>
		<Name>떡보</Name>
		<Amount>1</Amount>
		<Bill>15000</Bill>
		<Tags>콕 판매</Tags>
	</Account>
	<Account>
		<UID>14</UID>
		<Time>13:37:38</Time>
		<Name>용우</Name>
		<Amount>0</Amount>
		<Bill>5000</Bill>
		<Tags>일일 입장료</Tags>
	</Account>
	<Account>
		<UID>13</UID>
		<Time>13:36:46</Time>
		<Name>그레이</Name>
		<Amount>0</Amount>
		<Bill>5000</Bill>
		<Tags>일일 입장료</Tags>
	</Account>
	<Account>
		<UID>12</UID>
		<Time>13:35:37</Time>
		<Name>비가</Name>
		<Amount>0</Amount>
		<Bill>5000</Bill>
		<Tags>일일 입장료</Tags>
	</Account>
	<Account>
		<UID>11</UID>
		<Time>13:34:01</Time>
		<Name>라봉</Name>
		<Amount>0</Amount>
		<Bill>0</Bill>
		<Tags>일일 입장료 (카뱅)</Tags>
	</Account>
	<Account>
		<UID>10</UID>
		<Time>13:33:00</Time>
		<Name>이오</Name>
		<Amount>0</Amount>
		<Bill>0</Bill>
		<Tags>일일 입장료(5000원 카뱅)</Tags>
	</Account>
	<Account>
		<UID>9</UID>
		<Time>13:32:29</Time>
		<Name>기정</Name>
		<Amount>1</Amount>
		<Bill>16000</Bill>
		<Tags>콕 판매</Tags>
	</Account>
	<Account>
		<UID>8</UID>
		<Time>13:32:14</Time>
		<Name>기정</Name>
		<Amount>0</Amount>
		<Bill>5000</Bill>
		<Tags>일일 입장료</Tags>
	</Account>
	<Account>
		<UID>7</UID>
		<Time>13:31:47</Time>
		<Name>히오스</Name>
		<Amount>0</Amount>
		<Bill>5000</Bill>
		<Tags>일일 입장료</Tags>
	</Account>
	<Account>
		<UID>6</UID>
		<Time>13:31:39</Time>
		<Name>사자</Name>
		<Amount>0</Amount>
		<Bill>5000</Bill>
		<Tags>일일 입장료</Tags>
	</Account>
	<Account>
		<UID>5</UID>
		<Time>13:29:00</Time>
		<Name>물곰</Name>
		<Amount>0</Amount>
		<Bill>5000</Bill>
		<Tags>일일 입장료</Tags>
	</Account>
	<Account>
		<UID>4</UID>
		<Time>13:26:51</Time>
		<Name>대니</Name>
		<Amount>0</Amount>
		<Bill>5000</Bill>
		<Tags>일일 입장료</Tags>
	</Account>
	<Account>
		<UID>3</UID>
		<Time>13:25:11</Time>
		<Name>업</Name>
		<Amount>0</Amount>
		<Bill>0</Bill>
		<Tags>일일 입장료(5000원 카뱅)</Tags>
	</Account>
	<Account>
		<UID>2</UID>
		<Time>13:25:09</Time>
		<Name>떡보</Name>
		<Amount>0</Amount>
		<Bill>0</Bill>
		<Tags>일일 입장료(5000원 카뱅)</Tags>
	</Account>
	<Account>
		<UID>1</UID>
		<Time>13:25:06</Time>
		<Name>에스원</Name>
		<Amount>0</Amount>
		<Bill>0</Bill>
		<Tags>일일 입장료(5000원 카뱅)</Tags>
	</Account>
	<Account>
		<UID>0</UID>
		<Time>13:24:03</Time>
		<Name>라이언</Name>
		<Amount>0</Amount>
		<Bill>0</Bill>
		<Tags>일일 입장료(5000원 카뱅)</Tags>
	</Account>
	<Stock>
		<Name>콕 재고</Name>
		<Stock>13</Stock>
		<Current>7</Current>
		<Tags></Tags>
	</Stock>
	<Stock>
		<Name>현금</Name>
		<Stock>0</Stock>
		<Current>132000</Current>
		<Tags></Tags>
	</Stock>
	<Stock>
		<Name>입장한 회원 수</Name>
		<Stock>0</Stock>
		<Current>31</Current>
		<Tags></Tags>
	</Stock>
	<Stock>
		<Name>현재 게임중인 회원 수</Name>
		<Stock>0</Stock>
		<Current>26</Current>
		<Tags></Tags>
	</Stock>
	<Stock>
		<Name>전체 운용한 게임 수</Name>
		<Stock>0</Stock>
		<Current>41</Current>
		<Tags></Tags>
	</Stock>
	<Waiting>그레이</Waiting>
	<Waiting>떡보</Waiting>
	<Waiting>라이언</Waiting>
	<Waiting>사오</Waiting>
	<Waiting>업</Waiting>
	<Waiting>우솔</Waiting>
	<Waiting>지성</Waiting>
	<Waiting>코난</Waiting>
	<Waiting>피기</Waiting>
	<Waiting>현기</Waiting>
	<Attend>
		<그레이>
			<Name>그레이</Name>
			<EndTime>16:13:08</EndTime>
			<Enter>13:36:45</Enter>
			<Played>6</Played>
			<Variety>40.7%</Variety>
			<Paid>5000</Paid>
			<Level>700</Level>
			<Win>0</Win>
			<Lost>0</Lost>
			<Draw>6</Draw>
			<PlaySec>4678</PlaySec>
			<PlayTime>1시간 17분 58초 </PlayTime>
			<Tags></Tags>
			<Sd>1</Sd>
			<Avr>33</Avr>
			<Dev>261</Dev>
		</그레이>
		<기정>
			<Name>기정</Name>
			<EndTime>15:54:12</EndTime>
			<Enter>13:32:13</Enter>
			<Played>6</Played>
			<Variety>50.0%</Variety>
			<Paid>21000</Paid>
			<Level>400</Level>
			<Win>0</Win>
			<Lost>0</Lost>
			<Draw>5</Draw>
			<PlaySec>3887</PlaySec>
			<PlayTime>1시간 4분 47초 </PlayTime>
			<Tags></Tags>
			<Sd>1</Sd>
			<Avr>80</Avr>
			<Dev>313</Dev>
		</기정>
		<대니>
			<Name>대니</Name>
			<EndTime>15:56:59</EndTime>
			<Enter>13:26:50</Enter>
			<Played>6</Played>
			<Variety>34.6%</Variety>
			<Paid>5000</Paid>
			<Level>400</Level>
			<Win>0</Win>
			<Lost>0</Lost>
			<Draw>5</Draw>
			<PlaySec>4064</PlaySec>
			<PlayTime>1시간 7분 44초 </PlayTime>
			<Tags></Tags>
			<Sd>2</Sd>
			<Avr>-39</Avr>
			<Dev>135</Dev>
		</대니>
		<따당>
			<Name>따당</Name>
			<EndTime>15:56:59</EndTime>
			<Enter>14:21:26</Enter>
			<Played>5</Played>
			<Variety>33.3%</Variety>
			<Paid>0</Paid>
			<Level>400</Level>
			<Win>0</Win>
			<Lost>0</Lost>
			<Draw>4</Draw>
			<PlaySec>3046</PlaySec>
			<PlayTime>50분 46초 </PlayTime>
			<Tags></Tags>
			<Sd>1</Sd>
			<Avr>26</Avr>
			<Dev>212</Dev>
		</따당>
		<떡보>
			<Name>떡보</Name>
			<EndTime>16:22:30</EndTime>
			<Enter>13:25:06</Enter>
			<Played>6</Played>
			<Variety>48.0%</Variety>
			<Paid>15000</Paid>
			<Level>500</Level>
			<Win>0</Win>
			<Lost>0</Lost>
			<Draw>6</Draw>
			<PlaySec>5265</PlaySec>
			<PlayTime>1시간 27분 45초 </PlayTime>
			<Tags></Tags>
			<Sd>1</Sd>
			<Avr>41</Avr>
			<Dev>235</Dev>
		</떡보>
		<라봉>
			<Name>라봉</Name>
			<EndTime>16:10:26</EndTime>
			<Enter>13:33:58</Enter>
			<Played>7</Played>
			<Variety>40.0%</Variety>
			<Paid>0</Paid>
			<Level>900</Level>
			<Win>0</Win>
			<Lost>0</Lost>
			<Draw>6</Draw>
			<PlaySec>4154</PlaySec>
			<PlayTime>1시간 9분 14초 </PlayTime>
			<Tags></Tags>
			<Sd>3</Sd>
			<Avr>-100</Avr>
			<Dev>372</Dev>
		</라봉>
		<라이언>
			<Name>라이언</Name>
			<EndTime>16:01:25</EndTime>
			<Enter>13:24:00</Enter>
			<Played>5</Played>
			<Variety>45.8%</Variety>
			<Paid>0</Paid>
			<Level>200</Level>
			<Win>0</Win>
			<Lost>0</Lost>
			<Draw>5</Draw>
			<PlaySec>3493</PlaySec>
			<PlayTime>58분 13초 </PlayTime>
			<Tags></Tags>
			<Sd>1</Sd>
			<Avr>123</Avr>
			<Dev>345</Dev>
		</라이언>
		<로이>
			<Name>로이</Name>
			<EndTime>16:13:08</EndTime>
			<Enter>14:03:48</Enter>
			<Played>7</Played>
			<Variety>48.1%</Variety>
			<Paid>0</Paid>
			<Level>700</Level>
			<Win>0</Win>
			<Lost>0</Lost>
			<Draw>6</Draw>
			<PlaySec>4610</PlaySec>
			<PlayTime>1시간 16분 50초 </PlayTime>
			<Tags></Tags>
			<Sd>0</Sd>
			<Avr>4</Avr>
			<Dev>241</Dev>
		</로이>
		<물곰>
			<Name>물곰</Name>
			<EndTime>15:56:59</EndTime>
			<Enter>13:28:57</Enter>
			<Played>6</Played>
			<Variety>46.2%</Variety>
			<Paid>5000</Paid>
			<Level>500</Level>
			<Win>0</Win>
			<Lost>0</Lost>
			<Draw>5</Draw>
			<PlaySec>3647</PlaySec>
			<PlayTime>1시간 47초 </PlayTime>
			<Tags></Tags>
			<Sd>2</Sd>
			<Avr>-28</Avr>
			<Dev>108</Dev>
		</물곰>
		<비가>
			<Name>비가</Name>
			<EndTime>16:06:58</EndTime>
			<Enter>13:35:37</Enter>
			<Played>7</Played>
			<Variety>57.7%</Variety>
			<Paid>5000</Paid>
			<Level>750</Level>
			<Win>0</Win>
			<Lost>0</Lost>
			<Draw>6</Draw>
			<PlaySec>4158</PlaySec>
			<PlayTime>1시간 9분 18초 </PlayTime>
			<Tags></Tags>
			<Sd>2</Sd>
			<Avr>-205</Avr>
			<Dev>435</Dev>
		</비가>
		<사오>
			<Name>사오</Name>
			<EndTime>16:01:25</EndTime>
			<Enter>13:31:17</Enter>
			<Played>5</Played>
			<Variety>50.0%</Variety>
			<Paid>16000</Paid>
			<Level>400</Level>
			<Win>0</Win>
			<Lost>0</Lost>
			<Draw>5</Draw>
			<PlaySec>4230</PlaySec>
			<PlayTime>1시간 10분 30초 </PlayTime>
			<Tags></Tags>
			<Sd>2</Sd>
			<Avr>-34</Avr>
			<Dev>100</Dev>
		</사오>
		<사자>
			<Name>사자</Name>
			<EndTime>15:58:11</EndTime>
			<Enter>13:31:31</Enter>
			<Played>6</Played>
			<Variety>57.7%</Variety>
			<Paid>5000</Paid>
			<Level>700</Level>
			<Win>0</Win>
			<Lost>0</Lost>
			<Draw>5</Draw>
			<PlaySec>3903</PlaySec>
			<PlayTime>1시간 5분 3초 </PlayTime>
			<Tags></Tags>
			<Sd>0</Sd>
			<Avr>-56</Avr>
			<Dev>235</Dev>
		</사자>
		<산타>
			<Name>산타</Name>
			<EndTime>16:06:58</EndTime>
			<Enter>13:56:50</Enter>
			<Played>5</Played>
			<Variety>42.1%</Variety>
			<Paid>0</Paid>
			<Level>0</Level>
			<Win>0</Win>
			<Lost>0</Lost>
			<Draw>4</Draw>
			<PlaySec>3058</PlaySec>
			<PlayTime>50분 58초 </PlayTime>
			<Tags></Tags>
			<Sd>0</Sd>
			<Avr>406</Avr>
			<Dev>492</Dev>
		</산타>
		<업>
			<Name>업</Name>
			<EndTime>16:13:08</EndTime>
			<Enter>13:25:09</Enter>
			<Played>6</Played>
			<Variety>53.6%</Variety>
			<Paid>0</Paid>
			<Level>800</Level>
			<Win>0</Win>
			<Lost>0</Lost>
			<Draw>6</Draw>
			<PlaySec>4423</PlaySec>
			<PlayTime>1시간 13분 43초 </PlayTime>
			<Tags></Tags>
			<Sd>1</Sd>
			<Avr>-75</Avr>
			<Dev>295</Dev>
		</업>
		<에스원>
			<Name>에스원</Name>
			<EndTime>15:54:12</EndTime>
			<Enter>13:25:01</Enter>
			<Played>6</Played>
			<Variety>44.4%</Variety>
			<Paid>0</Paid>
			<Level>500</Level>
			<Win>0</Win>
			<Lost>0</Lost>
			<Draw>5</Draw>
			<PlaySec>3537</PlaySec>
			<PlayTime>58분 57초 </PlayTime>
			<Tags></Tags>
			<Sd>1</Sd>
			<Avr>11</Avr>
			<Dev>173</Dev>
		</에스원>
		<용우>
			<Name>용우</Name>
			<EndTime>16:06:58</EndTime>
			<Enter>13:37:34</Enter>
			<Played>7</Played>
			<Variety>50.0%</Variety>
			<Paid>5000</Paid>
			<Level>500</Level>
			<Win>0</Win>
			<Lost>0</Lost>
			<Draw>6</Draw>
			<PlaySec>4257</PlaySec>
			<PlayTime>1시간 10분 57초 </PlayTime>
			<Tags></Tags>
			<Sd>1</Sd>
			<Avr>61</Avr>
			<Dev>370</Dev>
		</용우>
		<우솔>
			<Name>우솔</Name>
			<EndTime>16:01:25</EndTime>
			<Enter>13:56:25</Enter>
			<Played>4</Played>
			<Variety>36.4%</Variety>
			<Paid>5000</Paid>
			<Level>100</Level>
			<Win>0</Win>
			<Lost>0</Lost>
			<Draw>4</Draw>
			<PlaySec>2960</PlaySec>
			<PlayTime>49분 20초 </PlayTime>
			<Tags></Tags>
			<Sd>1</Sd>
			<Avr>208</Avr>
			<Dev>411</Dev>
		</우솔>
		<쟈니>
			<Name>쟈니</Name>
			<EndTime>15:50:17</EndTime>
			<Enter>14:13:38</Enter>
			<Played>5</Played>
			<Variety>46.2%</Variety>
			<Paid>0</Paid>
			<Level>500</Level>
			<Win>0</Win>
			<Lost>0</Lost>
			<Draw>4</Draw>
			<PlaySec>2952</PlaySec>
			<PlayTime>49분 12초 </PlayTime>
			<Tags></Tags>
			<Sd>1</Sd>
			<Avr>70</Avr>
			<Dev>313</Dev>
		</쟈니>
		<제프>
			<Name>제프</Name>
			<EndTime>15:58:11</EndTime>
			<Enter>13:33:14</Enter>
			<Played>6</Played>
			<Variety>48.0%</Variety>
			<Paid>0</Paid>
			<Level>850</Level>
			<Win>0</Win>
			<Lost>0</Lost>
			<Draw>5</Draw>
			<PlaySec>3573</PlaySec>
			<PlayTime>59분 33초 </PlayTime>
			<Tags></Tags>
			<Sd>1</Sd>
			<Avr>-25</Avr>
			<Dev>185</Dev>
		</제프>
		<지성>
			<Name>지성</Name>
			<EndTime>16:22:30</EndTime>
			<Enter>14:16:32</Enter>
			<Played>5</Played>
			<Variety>42.3%</Variety>
			<Paid>20000</Paid>
			<Level>400</Level>
			<Win>0</Win>
			<Lost>0</Lost>
			<Draw>5</Draw>
			<PlaySec>4649</PlaySec>
			<PlayTime>1시간 17분 29초 </PlayTime>
			<Tags></Tags>
			<Sd>1</Sd>
			<Avr>86</Avr>
			<Dev>308</Dev>
		</지성>
		<코난>
			<Name>코난</Name>
			<EndTime>16:22:30</EndTime>
			<Enter>13:23:50</Enter>
			<Played>6</Played>
			<Variety>50.0%</Variety>
			<Paid>0</Paid>
			<Level>700</Level>
			<Win>0</Win>
			<Lost>0</Lost>
			<Draw>6</Draw>
			<PlaySec>5171</PlaySec>
			<PlayTime>1시간 26분 11초 </PlayTime>
			<Tags></Tags>
			<Sd>2</Sd>
			<Avr>-59</Avr>
			<Dev>243</Dev>
		</코난>
		<콕돌이>
			<Name>콕돌이</Name>
			<EndTime>16:10:26</EndTime>
			<Enter>13:23:46</Enter>
			<Played>7</Played>
			<Variety>33.3%</Variety>
			<Paid>0</Paid>
			<Level>900</Level>
			<Win>0</Win>
			<Lost>0</Lost>
			<Draw>6</Draw>
			<PlaySec>4454</PlaySec>
			<PlayTime>1시간 14분 14초 </PlayTime>
			<Tags></Tags>
			<Sd>3</Sd>
			<Avr>-48</Avr>
			<Dev>280</Dev>
		</콕돌이>
		<트윈스>
			<Name>트윈스</Name>
			<EndTime>15:56:59</EndTime>
			<Enter>14:03:51</Enter>
			<Played>5</Played>
			<Variety>30.8%</Variety>
			<Paid>5000</Paid>
			<Level>400</Level>
			<Win>0</Win>
			<Lost>0</Lost>
			<Draw>4</Draw>
			<PlaySec>3015</PlaySec>
			<PlayTime>50분 15초 </PlayTime>
			<Tags></Tags>
			<Sd>1</Sd>
			<Avr>-27</Avr>
			<Dev>109</Dev>
		</트윈스>
		<피기>
			<Name>피기</Name>
			<EndTime>16:22:30</EndTime>
			<Enter>13:48:33</Enter>
			<Played>6</Played>
			<Variety>36.0%</Variety>
			<Paid>0</Paid>
			<Level>500</Level>
			<Win>0</Win>
			<Lost>0</Lost>
			<Draw>6</Draw>
			<PlaySec>5243</PlaySec>
			<PlayTime>1시간 27분 23초 </PlayTime>
			<Tags></Tags>
			<Sd>1</Sd>
			<Avr>33</Avr>
			<Dev>216</Dev>
		</피기>
		<현기>
			<Name>현기</Name>
			<EndTime>16:13:08</EndTime>
			<Enter>13:32:45</Enter>
			<Played>7</Played>
			<Variety>55.6%</Variety>
			<Paid>0</Paid>
			<Level>700</Level>
			<Win>0</Win>
			<Lost>0</Lost>
			<Draw>7</Draw>
			<PlaySec>5448</PlaySec>
			<PlayTime>1시간 30분 48초 </PlayTime>
			<Tags></Tags>
			<Sd>3</Sd>
			<Avr>-65</Avr>
			<Dev>190</Dev>
		</현기>
		<히오스>
			<Name>히오스</Name>
			<EndTime>16:06:58</EndTime>
			<Enter>13:31:46</Enter>
			<Played>6</Played>
			<Variety>41.7%</Variety>
			<Paid>5000</Paid>
			<Level>200</Level>
			<Win>0</Win>
			<Lost>0</Lost>
			<Draw>5</Draw>
			<PlaySec>3856</PlaySec>
			<PlayTime>1시간 4분 16초 </PlayTime>
			<Tags></Tags>
			<Sd>3</Sd>
			<Avr>127</Avr>
			<Dev>378</Dev>
		</히오스>
	</Attend>
	<Leave>
		<비니>
			<Name>비니</Name>
			<EndTime>16:10:26</EndTime>
			<Enter>13:23:50</Enter>
			<Played>6</Played>
			<Variety>NA</Variety>
			<Paid>0</Paid>
			<Level>900</Level>
			<Win>0</Win>
			<Lost>0</Lost>
			<Draw>6</Draw>
			<PlaySec>4683</PlaySec>
			<PlayTime>1시간 18분 3초 </PlayTime>
			<Tags></Tags>
			<Sd>1</Sd>
			<Avr>-256</Avr>
			<Dev>555</Dev>
			<Leave>16:11:52</Leave>
		</비니>
		<야크모>
			<Name>야크모</Name>
			<EndTime>15:47:07</EndTime>
			<Enter>13:37:32</Enter>
			<Played>5</Played>
			<Variety>NA</Variety>
			<Paid>0</Paid>
			<Level>900</Level>
			<Win>0</Win>
			<Lost>0</Lost>
			<Draw>5</Draw>
			<PlaySec>3617</PlaySec>
			<PlayTime>1시간 17초 </PlayTime>
			<Tags></Tags>
			<Sd>3</Sd>
			<Avr>-124</Avr>
			<Dev>434</Dev>
			<Leave>15:48:44</Leave>
		</야크모>
		<이오>
			<Name>이오</Name>
			<EndTime>16:01:25</EndTime>
			<Enter>13:32:56</Enter>
			<Played>5</Played>
			<Variety>NA</Variety>
			<Paid>0</Paid>
			<Level>200</Level>
			<Win>0</Win>
			<Lost>0</Lost>
			<Draw>5</Draw>
			<PlaySec>3593</PlaySec>
			<PlayTime>59분 53초 </PlayTime>
			<Tags></Tags>
			<Sd>0</Sd>
			<Avr>180</Avr>
			<Dev>371</Dev>
			<Leave>16:10:44</Leave>
		</이오>
		<정훈>
			<Name>정훈</Name>
			<EndTime>16:10:26</EndTime>
			<Enter>13:42:44</Enter>
			<Played>6</Played>
			<Variety>NA</Variety>
			<Paid>0</Paid>
			<Level>850</Level>
			<Win>0</Win>
			<Lost>0</Lost>
			<Draw>6</Draw>
			<PlaySec>4203</PlaySec>
			<PlayTime>1시간 10분 3초 </PlayTime>
			<Tags></Tags>
			<Sd>1</Sd>
			<Avr>-67</Avr>
			<Dev>304</Dev>
			<Leave>16:10:39</Leave>
		</정훈>
		<제로>
			<Name>제로</Name>
			<EndTime>15:58:11</EndTime>
			<Enter>13:24:32</Enter>
			<Played>5</Played>
			<Variety>NA</Variety>
			<Paid>15000</Paid>
			<Level>700</Level>
			<Win>0</Win>
			<Lost>0</Lost>
			<Draw>5</Draw>
			<PlaySec>3329</PlaySec>
			<PlayTime>55분 29초 </PlayTime>
			<Tags></Tags>
			<Sd>1</Sd>
			<Avr>-57</Avr>
			<Dev>219</Dev>
			<Leave>15:58:46</Leave>
		</제로>
	</Leave>
	<GamePlaying>
		<Court>1</Court>
		<Members>에스원-기정-사자-쟈니</Members>
		<Title></Title>
		<Start>16:06:59</Start>
	</GamePlaying>
	<GamePlaying>
		<Court>2</Court>
		<Members>트윈스-물곰-따당-대니</Members>
		<Title></Title>
		<Start>16:10:27</Start>
	</GamePlaying>
	<GamePlaying>
		<Court>4</Court>
		<Members>제프-라봉-콕돌이 로이</Members>
		<Title></Title>
		<Start>16:13:10</Start>
	</GamePlaying>
	<GamePlaying>
		<Court>3</Court>
		<Members>용우-히오스-산타-비가</Members>
		<Title></Title>
		<Start>16:22:30</Start>
	</GamePlaying>
	<GameHistory>
		<Court>1</Court>
		<Members>그레이 용우 정훈 야크모</Members>
		<Title>Round#1(예약)</Title>
		<Start>13:50:44</Start>
		<Finish>13:57:48</Finish>
		<Elapsed>7분 4초</Elapsed>
		<ElapsedSec>424</ElapsedSec>
		<Score>0:0</Score>
	</GameHistory>
	<GameHistory>
		<Court>2</Court>
		<Members>라이언 라봉 비가 기정</Members>
		<Title>Round#1(예약)</Title>
		<Start>13:50:44</Start>
		<Finish>14:00:33</Finish>
		<Elapsed>9분 49초</Elapsed>
		<ElapsedSec>589</ElapsedSec>
		<Score>0:0</Score>
	</GameHistory>
	<GameHistory>
		<Court>3</Court>
		<Members>이오 업 제로 에스원</Members>
		<Title>Round#1(예약)</Title>
		<Start>13:50:44</Start>
		<Finish>14:01:05</Finish>
		<Elapsed>10분 21초</Elapsed>
		<ElapsedSec>621</ElapsedSec>
		<Score>0:0</Score>
	</GameHistory>
	<GameHistory>
		<Court>1</Court>
		<Members>비니-콕돌이-제프-현기</Members>
		<Title>Round#1</Title>
		<Start>13:57:48</Start>
		<Finish>14:12:37</Finish>
		<Elapsed>14분 49초</Elapsed>
		<ElapsedSec>889</ElapsedSec>
		<Score>0:0</Score>
	</GameHistory>
	<GameHistory>
		<Court>3</Court>
		<Members>물곰-대니-사오-히오스</Members>
		<Title>Round#1</Title>
		<Start>14:01:05</Start>
		<Finish>14:14:06</Finish>
		<Elapsed>13분 1초</Elapsed>
		<ElapsedSec>781</ElapsedSec>
		<Score>0:0</Score>
	</GameHistory>
	<GameHistory>
		<Court>2</Court>
		<Members>코난-사자-피기-떡보</Members>
		<Title>Round#1</Title>
		<Start>14:00:33</Start>
		<Finish>14:15:30</Finish>
		<Elapsed>14분 57초</Elapsed>
		<ElapsedSec>897</ElapsedSec>
		<Score>0:0</Score>
	</GameHistory>
	<GameHistory>
		<Court>1</Court>
		<Members>비가-정훈-제프-업</Members>
		<Title>Round#1</Title>
		<Start>14:12:38</Start>
		<Finish>14:23:17</Finish>
		<Elapsed>10분 39초</Elapsed>
		<ElapsedSec>639</ElapsedSec>
		<Score>0:0</Score>
	</GameHistory>
	<GameHistory>
		<Court>3</Court>
		<Members>야크모-콕돌이-라봉-비니</Members>
		<Title>Round#1</Title>
		<Start>14:14:07</Start>
		<Finish>14:25:55</Finish>
		<Elapsed>11분 48초</Elapsed>
		<ElapsedSec>708</ElapsedSec>
		<Score>0:0</Score>
	</GameHistory>
	<GameHistory>
		<Court>2</Court>
		<Members>현기-로이-제로-코난</Members>
		<Title>Round#1</Title>
		<Start>14:15:30</Start>
		<Finish>14:27:56</Finish>
		<Elapsed>12분 26초</Elapsed>
		<ElapsedSec>746</ElapsedSec>
		<Score>0:0</Score>
	</GameHistory>
	<GameHistory>
		<Court>1</Court>
		<Members>그레이-사자-물곰-피기</Members>
		<Title>Round#1</Title>
		<Start>14:23:18</Start>
		<Finish>14:37:34</Finish>
		<Elapsed>14분 16초</Elapsed>
		<ElapsedSec>856</ElapsedSec>
		<Score>0:0</Score>
	</GameHistory>
	<GameHistory>
		<Court>3</Court>
		<Members>에스원-용우-떡보-사오</Members>
		<Title>Round#1</Title>
		<Start>14:25:55</Start>
		<Finish>14:40:49</Finish>
		<Elapsed>14분 54초</Elapsed>
		<ElapsedSec>894</ElapsedSec>
		<Score>0:0</Score>
	</GameHistory>
	<GameHistory>
		<Court>2</Court>
		<Members>트윈스-대니-기정-이오</Members>
		<Title>Round#1</Title>
		<Start>14:27:57</Start>
		<Finish>14:41:18</Finish>
		<Elapsed>13분 21초</Elapsed>
		<ElapsedSec>801</ElapsedSec>
		<Score>0:0</Score>
	</GameHistory>
	<GameHistory>
		<Court>4</Court>
		<Members>히오스-라이언-우솔-산타</Members>
		<Title>Round#1</Title>
		<Start>14:34:25</Start>
		<Finish>14:46:38</Finish>
		<Elapsed>12분 13초</Elapsed>
		<ElapsedSec>733</ElapsedSec>
		<Score>0:0</Score>
	</GameHistory>
	<GameHistory>
		<Court>1</Court>
		<Members>지성-쟈니-따당-비니</Members>
		<Title></Title>
		<Start>14:37:34</Start>
		<Finish>14:51:26</Finish>
		<Elapsed>13분 52초</Elapsed>
		<ElapsedSec>832</ElapsedSec>
		<Score>0:0</Score>
	</GameHistory>
	<GameHistory>
		<Court>3</Court>
		<Members>콕돌이-정훈-라봉-제프</Members>
		<Title>Round#3</Title>
		<Start>14:40:50</Start>
		<Finish>14:52:59</Finish>
		<Elapsed>12분 9초</Elapsed>
		<ElapsedSec>729</ElapsedSec>
		<Score>0:0</Score>
	</GameHistory>
	<GameHistory>
		<Court>2</Court>
		<Members>야크모-업-코난-그레이</Members>
		<Title>Round#3</Title>
		<Start>14:41:18</Start>
		<Finish>14:56:46</Finish>
		<Elapsed>15분 28초</Elapsed>
		<ElapsedSec>928</ElapsedSec>
		<Score>0:0</Score>
	</GameHistory>
	<GameHistory>
		<Court>4</Court>
		<Members>비가-현기-사자-로이</Members>
		<Title>Round#3</Title>
		<Start>14:46:38</Start>
		<Finish>15:00:15</Finish>
		<Elapsed>13분 37초</Elapsed>
		<ElapsedSec>817</ElapsedSec>
		<Score>0:0</Score>
	</GameHistory>
	<GameHistory>
		<Court>3</Court>
		<Members>제로-용우-물곰-에스원</Members>
		<Title>Round#3</Title>
		<Start>14:53:02</Start>
		<Finish>15:03:00</Finish>
		<Elapsed>9분 58초</Elapsed>
		<ElapsedSec>598</ElapsedSec>
		<Score>0:0</Score>
	</GameHistory>
	<GameHistory>
		<Court>1</Court>
		<Members>쟈니-피기-떡보-기정</Members>
		<Title>Round#3</Title>
		<Start>14:53:34</Start>
		<Finish>15:06:55</Finish>
		<Elapsed>13분 21초</Elapsed>
		<ElapsedSec>801</ElapsedSec>
		<Score>0:0</Score>
	</GameHistory>
	<GameHistory>
		<Court>2</Court>
		<Members>지성-트윈스-따당-사오</Members>
		<Title>Round#3</Title>
		<Start>14:56:47</Start>
		<Finish>15:11:03</Finish>
		<Elapsed>14분 16초</Elapsed>
		<ElapsedSec>856</ElapsedSec>
		<Score>0:0</Score>
	</GameHistory>
	<GameHistory>
		<Court>4</Court>
		<Members>대니-라이언-이오-히오스</Members>
		<Title>Round#3</Title>
		<Start>15:00:16</Start>
		<Finish>15:13:34</Finish>
		<Elapsed>13분 18초</Elapsed>
		<ElapsedSec>798</ElapsedSec>
		<Score>0:0</Score>
	</GameHistory>
	<GameHistory>
		<Court>3</Court>
		<Members>우솔-산타-로이-현기</Members>
		<Title>Round#3</Title>
		<Start>15:03:01</Start>
		<Finish>15:16:02</Finish>
		<Elapsed>13분 1초 </Elapsed>
		<ElapsedSec>781</ElapsedSec>
		<Score>0:0</Score>
	</GameHistory>
	<GameHistory>
		<Court>1</Court>
		<Members>라봉-야크모-제프-콕돌이</Members>
		<Title>Round#4</Title>
		<Start>15:06:56</Start>
		<Finish>15:17:48</Finish>
		<Elapsed>10분 52초 </Elapsed>
		<ElapsedSec>652</ElapsedSec>
		<Score>0:0</Score>
	</GameHistory>
	<GameHistory>
		<Court>2</Court>
		<Members>비니-업-사자-그레이</Members>
		<Title>Round#4</Title>
		<Start>15:11:03</Start>
		<Finish>15:22:12</Finish>
		<Elapsed>11분 9초 </Elapsed>
		<ElapsedSec>669</ElapsedSec>
		<Score>0:0</Score>
	</GameHistory>
	<GameHistory>
		<Court>3</Court>
		<Members>정훈-로이-제로-비가</Members>
		<Title>Round#4</Title>
		<Start>15:16:03</Start>
		<Finish>15:27:43</Finish>
		<Elapsed>11분 40초 </Elapsed>
		<ElapsedSec>700</ElapsedSec>
		<Score>0:0</Score>
	</GameHistory>
	<GameHistory>
		<Court>1</Court>
		<Members>현기-코난-용우-쟈니</Members>
		<Title>Round#4</Title>
		<Start>15:17:48</Start>
		<Finish>15:28:59</Finish>
		<Elapsed>11분 11초 </Elapsed>
		<ElapsedSec>671</ElapsedSec>
		<Score>0:0</Score>
	</GameHistory>
	<GameHistory>
		<Court>4</Court>
		<Members>사오-기정-지성-대니</Members>
		<Title>Round#4</Title>
		<Start>15:14:50</Start>
		<Finish>15:32:02</Finish>
		<Elapsed>17분 12초 </Elapsed>
		<ElapsedSec>1032</ElapsedSec>
		<Score>0:0</Score>
	</GameHistory>
	<GameHistory>
		<Court>2</Court>
		<Members>떡보-물곰-피기-에스원</Members>
		<Title>Round#4</Title>
		<Start>15:22:17</Start>
		<Finish>15:34:57</Finish>
		<Elapsed>12분 40초 </Elapsed>
		<ElapsedSec>760</ElapsedSec>
		<Score>0:0</Score>
	</GameHistory>
	<GameHistory>
		<Court>3</Court>
		<Members>따당-트윈스-라이언-이오</Members>
		<Title>Round#4</Title>
		<Start>15:27:43</Start>
		<Finish>15:39:29</Finish>
		<Elapsed>11분 46초 </Elapsed>
		<ElapsedSec>706</ElapsedSec>
		<Score>0:0</Score>
	</GameHistory>
	<GameHistory>
		<Court>1</Court>
		<Members>히오스-우솔-산타-비니</Members>
		<Title>Round#4</Title>
		<Start>15:29:00</Start>
		<Finish>15:41:59</Finish>
		<Elapsed>12분 59초 </Elapsed>
		<ElapsedSec>779</ElapsedSec>
		<Score>0:0</Score>
	</GameHistory>
	<GameHistory>
		<Court>2</Court>
		<Members>라봉-업-로이-콕돌이</Members>
		<Title>Round#5</Title>
		<Start>15:34:57</Start>
		<Finish>15:46:07</Finish>
		<Elapsed>11분 10초 </Elapsed>
		<ElapsedSec>670</ElapsedSec>
		<Score>0:0</Score>
	</GameHistory>
	<GameHistory>
		<Court>4</Court>
		<Members>야크모-정훈-그레이-용우</Members>
		<Title>Round#5</Title>
		<Start>15:32:02</Start>
		<Finish>15:47:07</Finish>
		<Elapsed>15분 5초 </Elapsed>
		<ElapsedSec>905</ElapsedSec>
		<Score>0:0</Score>
	</GameHistory>
	<GameHistory>
		<Court>3</Court>
		<Members>현기-떡보-쟈니-비가</Members>
		<Title>Round#5</Title>
		<Start>15:39:29</Start>
		<Finish>15:50:17</Finish>
		<Elapsed>10분 48초 </Elapsed>
		<ElapsedSec>648</ElapsedSec>
		<Score>0:0</Score>
	</GameHistory>
	<GameHistory>
		<Court>1</Court>
		<Members>에스원-피기-지성-기정</Members>
		<Title>Round#5</Title>
		<Start>15:43:08</Start>
		<Finish>15:54:12</Finish>
		<Elapsed>11분 4초 </Elapsed>
		<ElapsedSec>664</ElapsedSec>
		<Score>0:0</Score>
	</GameHistory>
	<GameHistory>
		<Court>2</Court>
		<Members>물곰-트윈스-따당-대니</Members>
		<Title>Round#5</Title>
		<Start>15:46:07</Start>
		<Finish>15:56:59</Finish>
		<Elapsed>10분 52초 </Elapsed>
		<ElapsedSec>652</ElapsedSec>
		<Score>0:0</Score>
	</GameHistory>
	<GameHistory>
		<Court>4</Court>
		<Members>제프-코난-제로-사자</Members>
		<Title>Round#5</Title>
		<Start>15:47:07</Start>
		<Finish>15:58:11</Finish>
		<Elapsed>11분 4초 </Elapsed>
		<ElapsedSec>664</ElapsedSec>
		<Score>0:0</Score>
	</GameHistory>
	<GameHistory>
		<Court>3</Court>
		<Members>사오-이오-우솔-라이언</Members>
		<Title>Round#5</Title>
		<Start>15:50:18</Start>
		<Finish>16:01:25</Finish>
		<Elapsed>11분 7초 </Elapsed>
		<ElapsedSec>667</ElapsedSec>
		<Score>0:0</Score>
	</GameHistory>
	<GameHistory>
		<Court>1</Court>
		<Members>히오스-산타-비가-용우</Members>
		<Title>Round#5</Title>
		<Start>15:54:13</Start>
		<Finish>16:06:58</Finish>
		<Elapsed>12분 45초 </Elapsed>
		<ElapsedSec>765</ElapsedSec>
		<Score>0:0</Score>
	</GameHistory>
	<GameHistory>
		<Court>2</Court>
		<Members>콕돌이-정훈-라봉-비니</Members>
		<Title></Title>
		<Start>15:57:00</Start>
		<Finish>16:10:26</Finish>
		<Elapsed>13분 26초 </Elapsed>
		<ElapsedSec>806</ElapsedSec>
		<Score>0:0</Score>
	</GameHistory>
	<GameHistory>
		<Court>4</Court>
		<Members>현기-업-로이-그레이</Members>
		<Title></Title>
		<Start>15:58:12</Start>
		<Finish>16:13:08</Finish>
		<Elapsed>14분 56초 </Elapsed>
		<ElapsedSec>896</ElapsedSec>
		<Score>0:0</Score>
	</GameHistory>
	<GameHistory>
		<Court>3</Court>
		<Members>피기-지성-코난-떡보</Members>
		<Title></Title>
		<Start>16:01:25</Start>
		<Finish>16:22:30</Finish>
		<Elapsed>21분 5초 </Elapsed>
		<ElapsedSec>1265</ElapsedSec>
		<Score>0:0</Score>
	</GameHistory>
</root>
